magic_pdf/__init__.py
magic_pdf/pdf_parse_by_ocr.py
magic_pdf/pdf_parse_by_txt.py
magic_pdf/pdf_parse_union_core.py
magic_pdf/pdf_parse_union_core_v2.py
magic_pdf/user_api.py
magic_pdf/config/__init__.py
magic_pdf/config/enums.py
magic_pdf/config/exceptions.py
magic_pdf/data/__init__.py
magic_pdf/data/dataset.py
magic_pdf/data/read_api.py
magic_pdf/data/schemas.py
magic_pdf/data/utils.py
magic_pdf/data/data_reader_writer/__init__.py
magic_pdf/data/data_reader_writer/base.py
magic_pdf/data/data_reader_writer/filebase.py
magic_pdf/data/data_reader_writer/multi_bucket_s3.py
magic_pdf/data/data_reader_writer/s3.py
magic_pdf/data/io/__init__.py
magic_pdf/data/io/base.py
magic_pdf/data/io/http.py
magic_pdf/data/io/s3.py
magic_pdf/dict2md/__init__.py
magic_pdf/dict2md/mkcontent.py
magic_pdf/dict2md/ocr_mkcontent.py
magic_pdf/filter/__init__.py
magic_pdf/filter/pdf_classify_by_type.py
magic_pdf/filter/pdf_meta_scan.py
magic_pdf/integrations/__init__.py
magic_pdf/integrations/rag/__init__.py
magic_pdf/integrations/rag/api.py
magic_pdf/integrations/rag/type.py
magic_pdf/integrations/rag/utils.py
magic_pdf/layout/__init__.py
magic_pdf/layout/bbox_sort.py
magic_pdf/layout/layout_det_utils.py
magic_pdf/layout/layout_sort.py
magic_pdf/layout/layout_spiler_recog.py
magic_pdf/layout/mcol_sort.py
magic_pdf/libs/Constants.py
magic_pdf/libs/MakeContentConfig.py
magic_pdf/libs/ModelBlockTypeEnum.py
magic_pdf/libs/__init__.py
magic_pdf/libs/boxbase.py
magic_pdf/libs/calc_span_stats.py
magic_pdf/libs/clean_memory.py
magic_pdf/libs/commons.py
magic_pdf/libs/config_reader.py
magic_pdf/libs/convert_utils.py
magic_pdf/libs/coordinate_transform.py
magic_pdf/libs/detect_language_from_model.py
magic_pdf/libs/draw_bbox.py
magic_pdf/libs/drop_reason.py
magic_pdf/libs/drop_tag.py
magic_pdf/libs/hash_utils.py
magic_pdf/libs/json_compressor.py
magic_pdf/libs/language.py
magic_pdf/libs/local_math.py
magic_pdf/libs/markdown_utils.py
magic_pdf/libs/nlp_utils.py
magic_pdf/libs/ocr_content_type.py
lazyllm_magic_pdf-0.9.0.dist-info/LICENSE.md
lazyllm_magic_pdf-0.9.0.dist-info/METADATA
lazyllm_magic_pdf-0.9.0.dist-info/WHEEL
lazyllm_magic_pdf-0.9.0.dist-info/entry_points.txt
lazyllm_magic_pdf-0.9.0.dist-info/top_level.txt
lazyllm_magic_pdf-0.9.0.dist-info/RECORD
