Metadata-Version: 2.1
Name: lazyllm_magic_pdf
Version: 0.9.0
Summary: A practical tool for converting PDF to Markdown
Home-page: https://github.com/opendatalab/MinerU
Requires-Python: >=3.9
License-File: LICENSE.md
Requires-Dist: boto3 (>=1.28.43)
Requires-Dist: Brotli (>=1.1.0)
Requires-Dist: click (>=8.1.7)
Requires-Dist: fast-langdetect (==0.2.0)
Requires-Dist: loguru (>=0.6.0)
Requires-Dist: numpy (<2.0.0,>=1.21.6)
Requires-Dist: pdfminer.six (==20231228)
Requires-Dist: pydantic (<2.8.0,>=2.7.2)
Requires-Dist: PyMuPDF (>=1.24.9)
Requires-Dist: scikit-learn (>=1.0.2)
Requires-Dist: torch (<=2.3.1,>=2.2.2)
Requires-Dist: transformers
Provides-Extra: full
Requires-Dist: unimernet (==0.2.1) ; extra == 'full'
Requires-Dist: ultralytics ; extra == 'full'
Requires-Dist: paddleocr (==2.7.3) ; extra == 'full'
Requires-Dist: pypandoc ; extra == 'full'
Requires-Dist: struct-eqtable (==0.1.0) ; extra == 'full'
Requires-Dist: doclayout-yolo (==0.0.2b1) ; extra == 'full'
Requires-Dist: detectron2 ; extra == 'full'
Requires-Dist: paddlepaddle (==3.0.0b1) ; (platform_system == "Linux") and extra == 'full'
Requires-Dist: matplotlib ; (platform_system == "Linux" or platform_system == "Darwin") and extra == 'full'
Requires-Dist: matplotlib (<=3.9.0) ; (platform_system == "Windows") and extra == 'full'
Requires-Dist: paddlepaddle (==2.6.1) ; (platform_system == "Windows" or platform_system == "Darwin") and extra == 'full'
Provides-Extra: lite
Requires-Dist: paddleocr (==2.7.3) ; extra == 'lite'
Requires-Dist: paddlepaddle (==3.0.0b1) ; (platform_system == "Linux") and extra == 'lite'
Requires-Dist: paddlepaddle (==2.6.1) ; (platform_system == "Windows" or platform_system == "Darwin") and extra == 'lite'
